github/__init__.py
github/client.py
github/exception.py
github_recover-1.dist-info/LICENSE
github_recover-1.dist-info/METADATA
github_recover-1.dist-info/WHEEL
github_recover-1.dist-info/top_level.txt
github_recover-1.dist-info/RECORD
