Metadata-Version: 2.1
Name: github-recover
Version: 1
Summary: A small GitHub REST API client written in Python 
Home-page: https://github.com/metect
Author: amirali irvany
Author-email: dev.amirali.irvany@gmail.com
Classifier: Programming Language :: Python :: 3
Classifier: License :: OSI Approved :: MIT License
Requires-Python: >=3.6
License-File: LICENSE
Requires-Dist: requests
